{
   "store" : [
      "meteor",
      "npm:redux",
      "store/reducers/root"
   ],
   "methods/dispatchAction" : [
      "deanius:uni-method",
      "meteor",
      "client/methods",
      "server/methods"
   ],
   "store/reducers/root" : [
      "meteor",
      "npm:immutable/dist/immutable",
      "npm:redux-act",
      "npm:redux-immutable/dist",
      "store/reducers/game",
      "store/reducers/client/reset"
   ],
   "client/main" : [
      "routes",
      "client/serverActionsReceiver",
      "client/subscribeServerActions",
      "methods/dispatchAction"
   ],
   "client/subscribeServerActions" : [
      "meteor",
      "client/streams/serverActionsStream"
   ],
   "server/publications/serverActions" : [
      "store",
      "mongo",
      "server/publications/createPublication",
      "server/streams/clientUpdatesStream"
   ],
   "store/reducers/client/reset" : [
      "npm:redux-act"
   ],
   "test/spec.test" : [
      "meteor",
      "npm:chai"
   ],
   "store/reducers/game" : [
      "npm:redux-act"
   ],
   "client/streams/serverActionsStream" : [
      "npm:xstream"
   ],
   "client/serverActionsReceiver" : [
      "client/streams/serverActionsStream",
      "store"
   ],
   "server/main" : [
      "routes",
      "methods/dispatchAction",
      "server/publications/serverActions"
   ],
   "server/streams/incomingClientActions" : [
      "npm:rx"
   ],
   "server/methods" : [
      "npm:immutable/dist/immutable",
      "server/streams/incomingClientActions"
   ],
   "routes" : [
      "reactrouter:react-router-ssr",
      "npm:react-router",
      "npm:react"
   ],
   "client/methods" : [],
   "server/publications/createPublication" : [
      "meteor",
      "underscore"
   ],
   "server/streams/clientUpdatesStream" : [
      "server/streams/incomingClientActions"
   ]
}
